dtcc_viewer/__init__.py
dtcc_viewer/bounds.py
dtcc_viewer/building.py
dtcc_viewer/city.py
dtcc_viewer/citymodel.py
dtcc_viewer/grid.py
dtcc_viewer/linestring.py
dtcc_viewer/logging.py
dtcc_viewer/mesh.py
dtcc_viewer/multilinestring.py
dtcc_viewer/multisurface.py
dtcc_viewer/new_raster.py
dtcc_viewer/notebook_functions.py
dtcc_viewer/object.py
dtcc_viewer/pointcloud.py
dtcc_viewer/roadnetwork.py
dtcc_viewer/surface.py
dtcc_viewer/utils.py
dtcc_viewer/volume_grid.py
dtcc_viewer/volume_mesh.py
dtcc_viewer/opengl/__init__.py
dtcc_viewer/opengl/action.py
dtcc_viewer/opengl/camera.py
dtcc_viewer/opengl/data_wrapper.py
dtcc_viewer/opengl/environment.py
dtcc_viewer/opengl/gl_axes.py
dtcc_viewer/opengl/gl_grid.py
dtcc_viewer/opengl/gl_lines.py
dtcc_viewer/opengl/gl_mesh.py
dtcc_viewer/opengl/gl_model.py
dtcc_viewer/opengl/gl_object.py
dtcc_viewer/opengl/gl_points.py
dtcc_viewer/opengl/gl_quad.py
dtcc_viewer/opengl/gl_raster.py
dtcc_viewer/opengl/gui.py
dtcc_viewer/opengl/parameters.py
dtcc_viewer/opengl/parts.py
dtcc_viewer/opengl/scene.py
dtcc_viewer/opengl/utils.py
dtcc_viewer/opengl/window.py
dtcc_viewer/opengl/wrapper.py
dtcc_viewer/opengl/wrp_bounds.py
dtcc_viewer/opengl/wrp_building.py
dtcc_viewer/opengl/wrp_city.py
dtcc_viewer/opengl/wrp_geometries.py
dtcc_viewer/opengl/wrp_grid.py
dtcc_viewer/opengl/wrp_lines.py
dtcc_viewer/opengl/wrp_linestring.py
dtcc_viewer/opengl/wrp_mesh.py
dtcc_viewer/opengl/wrp_object.py
dtcc_viewer/opengl/wrp_pointcloud.py
dtcc_viewer/opengl/wrp_raster.py
dtcc_viewer/opengl/wrp_roadnetwork.py
dtcc_viewer/opengl/wrp_surface.py
dtcc_viewer/opengl/wrp_volume_mesh.py
dtcc_viewer/raster_mpl/MPLImageViewer.py
dtcc_viewer/raster_mpl/TkImageViewers.py
dtcc_viewer/raster_mpl/__init__.py
dtcc_viewer/raster_mpl/raster_web.py
dtcc_viewer/scripts/__init__.py
dtcc_viewer/scripts/main.py
dtcc_viewer/shaders/shaders_axes.py
dtcc_viewer/shaders/shaders_base_quad.py
dtcc_viewer/shaders/shaders_color_maps.py
dtcc_viewer/shaders/shaders_debug.py
dtcc_viewer-0.9.2.dist-info/LICENSE
dtcc_viewer-0.9.2.dist-info/METADATA
dtcc_viewer-0.9.2.dist-info/WHEEL
dtcc_viewer-0.9.2.dist-info/top_level.txt
dtcc_viewer-0.9.2.dist-info/RECORD
