Metadata-Version: 2.2
Name: dtcc-viewer
Version: 0.9.2
Summary: DTCC Viewer
Author-email: Jens Olsson <jens.olsson@chalmersindustriteknik.se>, Dag Wästberg <dwastberg@gmail.com>
Classifier: Intended Audience :: Science/Research
Classifier: Programming Language :: Python :: 3
Classifier: Programming Language :: C++
Classifier: License :: OSI Approved :: MIT License
Requires-Python: <3.13,>=3.10
License-File: LICENSE
Requires-Dist: jupyter
Requires-Dist: ipywidgets
Requires-Dist: matplotlib
Requires-Dist: colormap
Requires-Dist: numpy
Requires-Dist: folium>=0.14.0
Requires-Dist: pyglet
Requires-Dist: trimesh
Requires-Dist: pyopengl
Requires-Dist: pyglfw
Requires-Dist: pyrr
Requires-Dist: pillow
Requires-Dist: glfw
Requires-Dist: imgui
Requires-Dist: tqdm>=4.66.1
Requires-Dist: dtcc-core
Provides-Extra: test
Requires-Dist: pytest; extra == "test"
Provides-Extra: dev
Requires-Dist: easydev; extra == "dev"
Requires-Dist: black; extra == "dev"
